LICENSE
MANIFEST.in
README.rst
setup.cfg
setup.py
versioneer.py
garleek/__init__.py
garleek/_version.py
garleek/atom_types.py
garleek/cli.py
garleek/connectors.py
garleek/units.py
garleek.egg-info/PKG-INFO
garleek.egg-info/SOURCES.txt
garleek.egg-info/dependency_links.txt
garleek.egg-info/entry_points.txt
garleek.egg-info/requires.txt
garleek.egg-info/top_level.txt
garleek/data/atom_types/amber99_to_tinker
garleek/data/atom_types/charmm22_to_tinker
garleek/data/atom_types/mm3pro_to_tinker
garleek/data/atom_types/mmff
garleek/data/atom_types/uff_to_mm3
garleek/data/prm/amber99sb.prm
garleek/data/prm/amoeba09.prm
garleek/data/prm/biotyper.py
garleek/data/prm/charmm22.prm
garleek/data/prm/mm3.prm
garleek/data/prm/mm3pro.prm
garleek/data/prm/mmff.prm
garleek/data/prm/oplsaa.prm
garleek/data/prm/qmmm3.prm
garleek/data/prm/qmmmff.prm
garleek/mm/__init__.py
garleek/mm/tinker.py
garleek/qm/__init__.py
garleek/qm/gaussian.py