Metadata-Version: 1.1
Name: garleek
Version: 0.3.2
Summary: Garleek: An extra flavor to ONIOM
